Workbook

Sheet Simulador
B4: Variáveis
B5: Salário | D5: 4200
B6: Rendimento Carteira | D6: 0.006
B7: Sugestão Investimento (30%) | D7: =D5*0.3 -> 1260
B9: INVESTIMENTO MENSAL
B10: Quanto investir por mês? | D10: 1260
B11: Por quantos anos? | D11: 10
B12: Taxa de Rendimento Mensal? | D12: 0.01079
B13: Patrimônio acumulado | D13: =FV($D$12,$D$11 * 12,-$D$10) -> 306538.11
B14: Dividendo Mensais | D14: =D13*D6 -> 1839.2286
B16: Cenários | D16: Dividendo
A17: 2 | B17: Quanto em 2 anos? | C17: =FV($D$12,A17 * 12,-$D$10) -> 34306.81 | D17: =C17*$D$6 -> 205.84086
A18: 5 | B18: Quanto em 5 anos? | C18: =FV($D$12,A18 * 12,-$D$10) -> 105558.91 | D18: =C18*$D$6 -> 633.35347
A19: 10 | B19: Quanto em 10 anos? | C19: =FV($D$12,A19 * 12,-$D$10) -> 306538.11 | D19: =C19*$D$6 -> 1839.2286
A20: 20 | B20: Quanto em 20 anos? | C20: =FV($D$12,A20 * 12,-$D$10) -> 1417750 | D20: =C20*$D$6 -> 8506.4999
A21: 30 | B21: Quanto em 30 anos? | C21: =FV($D$12,A21 * 12,-$D$10) -> 5445933.8 | D21: =C21*$D$6 -> 32675.603
B23: Perfil | C23: Agressivo
B24: Valor a ser investido por mês | C24: =D10 -> 1260
B26: Tipo de FII | C26: Percentual Sugerido | D26: Valores
B27: Papel | C27: =VLOOKUP($C$23&"-"&B27,'Tabela de Apoio'!A3:D21,4,FALSE) -> 0.5 | D27: =$C$24*C27 -> 630
B28: Tijolo | C28: =VLOOKUP($C$23&"-"&B28,'Tabela de Apoio'!A4:D22,4,FALSE) -> 0.1 | D28: =$C$24*C28 -> 126
B29: Híbridos | C29: =VLOOKUP($C$23&"-"&B29,'Tabela de Apoio'!A5:D23,4,FALSE) -> 0.05 | D29: =$C$24*C29 -> 63
B30: FOFs | C30: =VLOOKUP($C$23&"-"&B30,'Tabela de Apoio'!A6:D24,4,FALSE) -> 0.05 | D30: =$C$24*C30 -> 63
B31: Desenvolvimento | C31: =VLOOKUP($C$23&"-"&B31,'Tabela de Apoio'!A7:D25,4,FALSE) -> 0.2 | D31: =$C$24*C31 -> 252
B32: Hotelarias | C32: =VLOOKUP($C$23&"-"&B32,'Tabela de Apoio'!A8:D26,4,FALSE) -> 0.1 | D32: =$C$24*C32 -> 126
D33: =SUM(D27:D32) -> 1260

Sheet Tabela de Apoio
A3: Chave | B3: Perfil | C3: Tipo de FII | D3: %
A4: =B4&"-"&C4 -> Conservador-Papel | B4: Conservador | C4: Papel | D4: 0.3
A5: =B5&"-"&C5 -> Conservador-Tijolo | B5: Conservador | C5: Tijolo | D5: 0.5
A6: =B6&"-"&C6 -> Conservador-Híbridos | B6: Conservador | C6: Híbridos | D6: 0.1
A7: =B7&"-"&C7 -> Conservador-FOFs | B7: Conservador | C7: FOFs | D7: 0.1
A8: =B8&"-"&C8 -> Conservador-Desenvolvimento | B8: Conservador | C8: Desenvolvimento | D8: 0
A9: =B9&"-"&C9 -> Conservador-Hotelarias | B9: Conservador | C9: Hotelarias | D9: 0
A10: =B10&"-"&C10 -> Moderado-Papel | B10: Moderado | C10: Papel | D10: 0.32
A11: =B11&"-"&C11 -> Moderado-Tijolo | B11: Moderado | C11: Tijolo | D11: 0.4
A12: =B12&"-"&C12 -> Moderado-Híbridos | B12: Moderado | C12: Híbridos | D12: 0.08
A13: =B13&"-"&C13 -> Moderado-FOFs | B13: Moderado | C13: FOFs | D13: 0.05
A14: =B14&"-"&C14 -> Moderado-Desenvolvimento | B14: Moderado | C14: Desenvolvimento | D14: 0.05
A15: =B15&"-"&C15 -> Moderado-Hotelarias | B15: Moderado | C15: Hotelarias | D15: 0.1
... A21: =B21&"-"&C21 -> Agressivo-Hotelarias | B21: Agressivo | C21: Hotelarias | D21: 0.1
